mindspore/.commit_id
mindspore/__init__.py
mindspore/_c_dataengine.cpython-312-darwin.so
mindspore/_c_expression.cpython-312-darwin.so
mindspore/_c_mindrecord.cpython-312-darwin.so
mindspore/_check_jit_forbidden_api.py
mindspore/_checkparam.py
mindspore/_profiler.py
mindspore/amp.py
mindspore/context.py
mindspore/default_config.py
mindspore/device_manager.py
mindspore/log.py
mindspore/version.py
mindspore/_extends/__init__.py
mindspore/_extends/ast_checker.py
mindspore/_extends/builtin_operations.py
mindspore/_extends/utils.py
mindspore/_extends/graph_kernel/__init__.py
mindspore/_extends/graph_kernel/parallel_estimate.py
mindspore/_extends/graph_kernel/splitter.py
mindspore/_extends/graph_kernel/utils.py
mindspore/_extends/graph_kernel/model/__init__.py
mindspore/_extends/graph_kernel/model/graph_parallel.py
mindspore/_extends/graph_kernel/model/graph_split.py
mindspore/_extends/graph_kernel/model/model.py
mindspore/_extends/graph_kernel/model/model_builder.py
mindspore/_extends/optimize/__init__.py
mindspore/_extends/optimize/cell_utils.py
mindspore/_extends/parallel_compile/__init__.py
mindspore/_extends/parallel_compile/akg_compiler/__init__.py
mindspore/_extends/parallel_compile/akg_compiler/akg_process.py
mindspore/_extends/parallel_compile/akg_compiler/build_tbe_kernel.py
mindspore/_extends/parallel_compile/akg_compiler/compiler.py
mindspore/_extends/parallel_compile/akg_compiler/custom.py
mindspore/_extends/parallel_compile/akg_compiler/gen_custom_op_files.py
mindspore/_extends/parallel_compile/akg_compiler/get_file_path.py
mindspore/_extends/parallel_compile/akg_compiler/tbe_topi.py
mindspore/_extends/parallel_compile/akg_compiler/util.py
mindspore/_extends/parse/__init__.py
mindspore/_extends/parse/compile_config.py
mindspore/_extends/parse/namespace.py
mindspore/_extends/parse/parser.py
mindspore/_extends/parse/resources.py
mindspore/_extends/parse/standard_method.py
mindspore/_extends/parse/trope.py
mindspore/_extends/parse/deprecated/__init__.py
mindspore-2.8.0.dist-info/METADATA
mindspore-2.8.0.dist-info/WHEEL
mindspore-2.8.0.dist-info/entry_points.txt
mindspore-2.8.0.dist-info/top_level.txt
mindspore-2.8.0.dist-info/RECORD
